src/Appmain.py
src/Menu_logic.py
src/MostrarReserva_logi.py
src/Reserva_logic.py
src/__init__.py
src/validacion.py
ui/Menu.py
ui/MostrarReserva.py
ui/Reserva.py
ui/__init__.py
Reservas-0.1.0.dist-info/METADATA
Reservas-0.1.0.dist-info/WHEEL
Reservas-0.1.0.dist-info/top_level.txt
Reservas-0.1.0.dist-info/RECORD
