Metadata-Version: 2.1
Name: Reservas
Version: 0.1.0
Summary: Descripción breve de tu paquete
Author: Navil Lugo Taveras
Author-email: nafa8@hotmail.com
Classifier: Programming Language :: Python :: 3
Classifier: License :: OSI Approved :: MIT License
Classifier: Operating System :: OS Independent
Requires-Python: >=3.6
